Workbook

Sheet Bilgi
A1: Amaç | B1: TCMB döviz çıkış istatistik kodlarının (kaynak: İstatistik Kod Bazlı Kategori sayfası, F sütunu) Katar Merkez Bankası Purpose of Payment (PoP) kodları ile eşleştirilmesi.
A2: Yön mantığı | B2: İstatistik kodları Türkiye'den yurt dışına ÇIKIŞ işlemleridir. Ödeme Katar'a gittiğinde Katar tarafında GELEN ödeme olur; bu yüzden QAR listesindeki 'A' (receipt/inward) kodları ile eşleştirilmiştir. Örn: ithalat ödemesi (TR) → ihracat tahsilatı (QAR).
A3: Eşleştirme formatı | B3: İstatistikKodu-QARKodu (örn. 5807-A2J02). A sütunu formülle üretilir; D sütunundaki QAR kodu değiştirilirse A ve E sütunları otomatik güncellenir (D sütununda açılır liste vardır).
A4: Eşleşme Derecesi | B4: Tam: anlam birebir örtüşüyor. Yakın: ana amaç örtüşüyor, kapsam/taraf farkı var. Genel / En yakın: QAR listesinde karşılığı yok, en uygun genel kod seçildi — operasyon/uyum ekibi teyit etmeli.
A5: Mükerrer kodlar | B5: Kaynakta birden fazla kategoride geçen kodlar (örn. 5446, 5447, 7500) tek satırda birleştirildi; tüm kategoriler H sütununda listelenmiştir.
A6: Kapsam | B6: 281 benzersiz istatistik kodu, 85 QAR PoP kodu. Aynı QAR kodu birden fazla istatistik koduna karşılık gelebilir ('QAR Kodları' sayfasında sayısı görülebilir).
A7: Uyarı | B7: Eşleştirme, açıklama metinlerine göre yapılmış bir öneridir. Katar'daki muhabir/alıcı bankanın kendi kural setiyle canlı kullanım öncesi teyit edilmesi önerilir.

Sheet Eşleştirme
A1: Eşleştirme (İst. Kodu-QAR) | B1: İstatistik Kodu | C1: İstatistik Kod Açıklaması (TR) | D1: QAR PoP Kodu | E1: QAR Purpose of Payment Narration (EN) | F1: Eşleşme Derecesi | G1: Not / Gerekçe | H1: TCMB Ödeme Kategorisi
A2: =B2&"-"&D2 -> 5120-A1A01 | B2: 5120 | C2: Yurtiçinde yerleşik kişilere ait deniz, hava ve kara taşıtlarına yurt limanlarda sağlanan yakıt ve kumanya bedeli (Deniz taşıtlarına ilişkin olarak, bir gemi işletmecisinin birçok farklı ülkede kayıtlı gemisi bulunabilmektedir. Gemi işletmecilerinin yerleşikliğinin tespit edilmesinde, gemilerdeki elverişli bayrak - gemi sahibinin gemisine kendi ülkesinin bayrağı yerine çeşitli kolaylıklar gösteren bir başka devletin bayrağını çekmesi - kullanılmamalıdır. Yerleşiklik için gemicilik faaliyetini yürüten işletmenin bulunduğu ülke esas alınmalıdır.) | D2: A1A01 | E2: =IFERROR(INDEX('QAR Kodları'!$B:$B,MATCH(D2,'QAR Kodları'!$A:$A,0)),"KOD BULUNAMADI") -> Value of export bills negotiated/purchased/discounted etc | F2: Genel / En yakın | G2: Limanlarda sağlanan yakıt/kumanya (mal niteliğinde). | H2: 30) Taşımacılık ve lojistik hizmetleri
A3: =B3&"-"&D3 -> 5445-A1A01 | B3: 5445 | C3: Leasing kontratına bağlı olarak ödenen ithalat mal F.O.B. bedeli (Navlun ve sigorta hariç) | D3: A1A01 | E3: =IFERROR(INDEX('QAR Kodları'!$B:$B,MATCH(D3,'QAR Kodları'!$A:$A,0)),"KOD BULUNAMADI") -> Value of export bills negotiated/purchased/discounted etc | F3: Yakın | G3: Leasing'e bağlı ithalat mal bedeli. | H3: 9) İthalat/İhracat Ödemesi İşlemleri (Gümrük Komisyonları Dahil)
A4: =B4&"-"&D4 -> 5446-A1A02 | B4: 5446 | C4: 1996 yıl başından itibaren başlayan, Kabul Kredili Mal Mukabili ve Mal Mukabili İthalat işlemleri nedeniyle yapılan FOB ithalat ödemeleri (Navlun ve sigorta hariç) | D4: A1A02 | E4: =IFERROR(INDEX('QAR Kodları'!$B:$B,MATCH(D4,'QAR Kodları'!$A:$A,0)),"KOD BULUNAMADI") -> Realization of export bills (in respect of goods) sent on collection (full invoice value) | F4: Tam | G4: Mal mukabili / vesaik mukabili tahsil. | H4: 9) İthalat/İhracat Ödemesi İşlemleri (Gümrük Komisyonları Dahil); 38) Kıymetli maden ithalat ödemesi
A5: =B5&"-"&D5 -> 5447-A1A03 | B5: 5447 | C5: Peşin ödeme ile yapılan ithalat mal F.O.B. bedeli (Navlun ve sigorta hariç) | D5: A1A03 | E5: =IFERROR(INDEX('QAR Kodları'!$B:$B,MATCH(D5,'QAR Kodları'!$A:$A,0)),"KOD BULUNAMADI") -> Advance receipts against export contracts (export of goods only) | F5: Tam | G5: Peşin ödeme = ihracat sözleşmesine karşı avans tahsili. | H5: 9) İthalat/İhracat Ödemesi İşlemleri (Gümrük Komisyonları Dahil); 38) Kıymetli maden ithalat ödemesi
A6: =B6&"-"&D6 -> 5448-A1A01 | B6: 5448 | C6: Yurtiçinde yerleşik diğer bir bankada başlayan ithalat işlemleri sonucunda oluşan kısa vadeli ithalat borçlarına ilişkin ödenen ithalat mal F.O.B. bedeli (Navlun ve sigorta hariç) | D6: A1A01 | E6: =IFERROR(INDEX('QAR Kodları'!$B:$B,MATCH(D6,'QAR Kodları'!$A:$A,0)),"KOD BULUNAMADI") -> Value of export bills negotiated/purchased/discounted etc | F6: Yakın | G6: Başka bankada başlayan ithalatın borç ödemesi. | H6: 9) İthalat/İhracat Ödemesi İşlemleri (Gümrük Komisyonları Dahil); 38) Kıymetli maden ithalat ödemesi
A7: =B7&"-"&D7 -> 5700-A2A04 | B7: 5700 | C7: İhracat navlunu (DENİZ): Yurtiçinde yerleşik kişiler tarafından yurtdışında yerleşik kişilere Türkiye'den yurtdışına yapılan ihracat nedeniyle ödenen navlun bedelleri | D7: A2A04 | E7: =IFERROR(INDEX('QAR Kodları'!$B:$B,MATCH(D7,'QAR Kodları'!$A:$A,0)),"KOD BULUNAMADI") -> Freight on exports-shipping companies | F7: Tam | G7: Deniz navlunu. | H7: 30) Taşımacılık ve lojistik hizmetleri
A8: =B8&"-"&D8 -> 5701-A2A04 | B8: 5701 | C8: İthalat navlunu: Yurtiçinde yerleşik kişiler tarafından yurtdışında yerleşik kişilere Türkiye'ye yapılan ithalat nedeniyle ödenen navlun bedelleri | D8: A2A04 | E8: =IFERROR(INDEX('QAR Kodları'!$B:$B,MATCH(D8,'QAR Kodları'!$A:$A,0)),"KOD BULUNAMADI") -> Freight on exports-shipping companies | F8: Tam | G8: Deniz navlunu. | H8: 30) Taşımacılık ve lojistik hizmetleri
A9: =B9&"-"&D9 -> 5702-A2A04 | B9: 5702 | C9: Transit taşımacılık navlunu (DENİZ): Yurtiçinde yerleşik kişiler tarafından transit olarak yapılan mal nakliyatı nedeniyle yurtdışında yerleşik kişilere ödenen navlun bedelleri | D9: A2A04 | E9: =IFERROR(INDEX('QAR Kodları'!$B:$B,MATCH(D9,'QAR Kodları'!$A:$A,0)),"KOD BULUNAMADI") -> Freight on exports-shipping companies | F9: Tam | G9: Deniz navlunu. | H9: 30) Taşımacılık ve lojistik hizmetleri
A10: =B10&"-"&D10 -> 5703-A2A01 | B10: 5703 | C10: Uluslararası yolcu taşımacılığı (DENİZ): Yurtdışında yerleşik kişiler tarafından yurtiçinde yerleşik kişilere sağlanan yolcu bileti, fazla bagaj gibi taşımacılık hizmetleri ile yurtiçinde yerleşik kişilere mürettebatıyla birlikte kısa süreli taşıt kiralanması nedeniyle ödenen bedeller | D10: A2A01 | E10: =IFERROR(INDEX('QAR Kodları'!$B:$B,MATCH(D10,'QAR Kodları'!$A:$A,0)),"KOD BULUNAMADI") -> Inward remittance on account of surplus freight/passenger fare by Qatari shipping companies operating abroad | F10: Yakın | G10: Deniz yolcu taşımacılığı. Mürettebatlı kiralama ise A2A05. | H10: 30) Taşımacılık ve lojistik hizmetleri
A11: =B11&"-"&D11 -> 5704-A2A13 | B11: 5704 | C11: Diğer taşımacılık hizmetleri (DENİZ): Yurtiçinde yerleşik kişilere yurtdışı limanlarda sağlanan kargo yükleme/boşaltma, depolama, temizleme, çekme, kurtarma vb. hizmetleri ile yurtiçindeki liman, havalimanı, tren istasyonu, terminal gibi tesislerin işletilmesi nedeniyle yurtdışında yerleşik kişilere ödenen bedeller | D11: A2A13 | E11: =IFERROR(INDEX('QAR Kodları'!$B:$B,MATCH(D11,'QAR Kodları'!$A:$A,0)),"KOD BULUNAMADI") -> Receipts towards other transportation services (stevedoring demurrage port handling charges etc | F11: Tam | G11: Liman hizmetleri, yükleme-boşaltma vb. | H11: 30) Taşımacılık ve lojistik hizmetleri
A12: =B12&"-"&D12 -> 5705-A2A10 | B12: 5705 | C12: İhracat navlunu (HAVA) : Yurtiçinde yerleşik kişiler tarafından yurtdışında yerleşik kişilere Türkiye'den yurtdışına yapılan ihracat nedeniyle ödenen navlun bedelleri | D12: A2A10 | E12: =IFERROR(INDEX('QAR Kodları'!$B:$B,MATCH(D12,'QAR Kodları'!$A:$A,0)),"KOD BULUNAMADI") -> Freight on exports-airlines companies | F12: Tam | G12: Hava navlunu. | H12: 30) Taşımacılık ve lojistik hizmetleri
A13: =B13&"-"&D13 -> 5706-A2A10 | B13: 5706 | C13: İthalat navlunu: Yurtiçinde yerleşik kişiler tarafından yurtdışında yerleşik kişilere Türkiye'ye yapılan ithalat nedeniyle ödenen navlun bedelleri | D13: A2A10 | E13: =IFERROR(INDEX('QAR Kodları'!$B:$B,MATCH(D13,'QAR Kodları'!$A:$A,0)),"KOD BULUNAMADI") -> Freight on exports-airlines companies | F13: Tam | G13: Hava navlunu. | H13: 30) Taşımacılık ve lojistik hizmetleri
... A28: =B28&"-"&D28 -> 5721-A2K02 | B28: 5721 | C28: Posta ve Kurye Hizmetleri Yurtdışında yerleşik kişiler tarafından yurtiçinde yerleşik kişilere sağlanan posta ve kurye hizmetleri nedeniyle ödenen bedeller | D28: A2K02 | E28: =IFERROR(INDEX('QAR Kodları'!$B:$B,MATCH(D28,'QAR Kodları'!$A:$A,0)),"KOD BULUNAMADI") -> Receipts on account of settlement of claims for courier services | F28: Yakın | G28: Kurye hizmetleri. Posta ise A2K01. | H28: 30) Taşımacılık ve lojistik hizmetleri
A29: =B29&"-"&D29 -> 5730-A2B01 | B29: 5730 | C29: Seyahat giderleri-Kurs-Kongre-Tatil-Eğitim-Tedavi-Hac (Tesis edilen seyahat çek bedelleri de muhabire borç kaydedildiği zaman bu kod altında bildirilecektir) | D29: A2B01 | E29: =IFERROR(INDEX('QAR Kodları'!$B:$B,MATCH(D29,'QAR Kodları'!$A:$A,0)),"KOD BULUNAMADI") -> Inward remittance towards business travel includes purchases of foreign tcs,currency notes etc. Over the counter by hotels,hospitals,emporium | F29: Tam | H29: 34) Seyahat, turizm, eğitim ve sağlık hizmetleri
A30: =B30&"-"&D30 -> 5740-A2D01 | B30: 5740 | C30: Yurtdışında gerçekleştirilen inşaat hizmetleri giderleri: Yurtiçinde yerleşik kişiler tarafından yurtdışında gerçekleştirilen inşaat hizmetleri ile ilgili olarak, yurtdışında yerleşik kişilerden sağlanan mal ve hizmetler nedeniyle ödenen bedeller (Hazırlık avansları dahil) | D30: A2D01 | E30: =IFERROR(INDEX('QAR Kodları'!$B:$B,MATCH(D30,'QAR Kodları'!$A:$A,0)),"KOD BULUNAMADI") -> Inward remittance towards meeting the cost of construction of projects in Qatar | F30: Tam | G30: Katar'da gerçekleştirilen inşaat projesi giderleri. | H30: 28) Ticaret ve endüstri hizmetleri
A31: =B31&"-"&D31 -> 5741-A2D01 | B31: 5741 | C31: Yurtiçinde gerçekleştirilen inşaat hizmetleri giderleri: Yurtdışında yerleşik kişiler tarafından yurtiçinde gerçekleştirilen inşaat hizmetleri nedeniyle ödenen bedeller | D31: A2D01 | E31: =IFERROR(INDEX('QAR Kodları'!$B:$B,MATCH(D31,'QAR Kodları'!$A:$A,0)),"KOD BULUNAMADI") -> Inward remittance towards meeting the cost of construction of projects in Qatar | F31: Genel / En yakın | G31: Türkiye'de yabancı müteahhit inşaat bedeli; QAR'da yurt dışı inşaat ayrımı yok. | H31: 28) Ticaret ve endüstri hizmetleri
A32: =B32&"-"&D32 -> 5750-A2C01 | B32: 5750 | C32: Hayat sigortası: Yurtiçinde yerleşik gerçek kişiler tarafından yurtdışında yerleşik sigorta şirketlerine yapılan prim ödemeleri ile yurtiçinde yerleşik sigorta şirketlerinin hayat sigortası ile ilgili olarak yurtdışında yerleşik gerçek kişilere yaptıkları ödemeler (Ölüme bağlı hayat sigortasına ilişkin bedeller hariç tutulacaktır) | D32: A2C01 | E32: =IFERROR(INDEX('QAR Kodları'!$B:$B,MATCH(D32,'QAR Kodları'!$A:$A,0)),"KOD BULUNAMADI") -> Receipts on account of life insurance premium | F32: Tam | H32: 31) Sigorta ve reasürans hizmetleri
A33: =B33&"-"&D33 -> 5751-A2C01 | B33: 5751 | C33: Emeklilik hizmetleri: Yurtiçinde yerleşik gerçek kişiler tarafından yurtdışında yerleşik sigorta şirketlerine yapılan prim ödemeleri ile yurtiçinde yerleşik sigorta şirketlerinin emeklilik hizmetleri ile ilgili olarak yurtdışında yerleşik gerçek kişilere yaptıkları ödemeler | D33: A2C01 | E33: =IFERROR(INDEX('QAR Kodları'!$B:$B,MATCH(D33,'QAR Kodları'!$A:$A,0)),"KOD BULUNAMADI") -> Receipts on account of life insurance premium | F33: Genel / En yakın | G33: Emeklilik hizmetleri; QAR'da ayrı kod yok. | H33: 35) Kişisel gelir ve harcamalar, ücret ve emeklilik ödemeleri
A34: =B34&"-"&D34 -> 5752-A2C02 | B34: 5752 | C34: Navlun sigortası: Yurtiçinde yerleşik kişilerin mal taşımacılığı alanında aldıkları sigortacılık hizmetlerinden dolayı yurtdışında yerleşik sigorta şirketlerine ödedikleri primler ile yurtiçinde yerleşik sigorta şirketlerinin bu kapsamda yurtdışında yerleşik kişilere yaptıkları tazminat ödemeleri | D34: A2C02 | E34: =IFERROR(INDEX('QAR Kodları'!$B:$B,MATCH(D34,'QAR Kodları'!$A:$A,0)),"KOD BULUNAMADI") -> Receipts on account of freight insurance relating to import & export goods | F34: Tam | H34: 31) Sigorta ve reasürans hizmetleri
A35: =B35&"-"&D35 -> 5753-A2C03 | B35: 5753 | C35: Diğer doğrudan sigorta: Yurtiçinde yerleşik kişilerin, hayat, emeklilik ve navlun sigortası dışındaki ölüme bağlı hayat sigortası, özel sağlık sigortası ile kaza, yangın, doğal afet, seyahat, kredi kartı sigortası gibi alanlarda aldıkları sigortacılık hizmetlerinden dolayı yurtdışında yerleşik sigorta şirketlerine ödedikleri primler ile yurtiçinde yerleşik sigorta şirketlerinin bu kapsamda yurtdışında yerleşik gerçek kişilere yaptıkları tazminat ödemeleri (Ölüme bağlı hayat sigortasına ilişkin bedeller bu kod altında bildirilecektir.) | D35: A2C03 | E35: =IFERROR(INDEX('QAR Kodları'!$B:$B,MATCH(D35,'QAR Kodları'!$A:$A,0)),"KOD BULUNAMADI") -> Receipts of other general insurance premium | F35: Tam | H35: 31) Sigorta ve reasürans hizmetleri
A36: =B36&"-"&D36 -> 5754-A2C04 | B36: 5754 | C36: Reasürans: Yurtiçinde yerleşik reasürörlerin, yurtdışında yerleşik sedan şirketlerine yaptıkları hasar ödemeleri ile yurtiçinde yerleşik sedan şirketlerinin reasürans nedeniyle yurtdışında yerleşik reasürörlere devrettikleri primler | D36: A2C04 | E36: =IFERROR(INDEX('QAR Kodları'!$B:$B,MATCH(D36,'QAR Kodları'!$A:$A,0)),"KOD BULUNAMADI") -> Receipts on account of reinsurance premium | F36: Tam | H36: 31) Sigorta ve reasürans hizmetleri
A37: =B37&"-"&D37 -> 5755-A2C03 | B37: 5755 | C37: Standartlaştırılmış garanti hizmetleri: Yurtiçinde yerleşik kişiler tarafından yurtdışında yerleşik sigorta şirketlerine garantör hizmetleri, ihracat kredi garantisi vb. için yapılan prim ödemeleri ile yurtiçinde yerleşik sigorta şirketlerinin bu kapsamda yurtdışında yerleşik kişilere yaptıkları tazminat ödemeleri | D37: A2C03 | E37: =IFERROR(INDEX('QAR Kodları'!$B:$B,MATCH(D37,'QAR Kodları'!$A:$A,0)),"KOD BULUNAMADI") -> Receipts of other general insurance premium | F37: Yakın | G37: Standart garanti hizmetleri (ihracat kredi garantisi vb.). | H37: 31) Sigorta ve reasürans hizmetleri
A38: =B38&"-"&D38 -> 5756-A2C05 | B38: 5756 | C38: Sigortacılık yardımcı hizmetleri: Yurtiçinde yerleşik kişilerin, her türlü sigorta işlemleri nedeniyle yurtdışında yerleşik kişilere ödedikleri acente komisyonu, danışmanlık hizmet bedelleri ve benzeri giderler | D38: A2C05 | E38: =IFERROR(INDEX('QAR Kodları'!$B:$B,MATCH(D38,'QAR Kodları'!$A:$A,0)),"KOD BULUNAMADI") -> Receipts on account of auxiliary services (commission on insurance) | F38: Tam | H38: 31) Sigorta ve reasürans hizmetleri
A39: =B39&"-"&D39 -> 5760-A2F01 | B39: 5760 | C39: Yurtdışında yerleşik kişilerden alınan finansal aracılık ve finansal nitelikli danışmanlık, saklama ve varlık yönetimi gibi hizmetler nedeniyle ödenen her türlü hizmet komisyonu ve benzeri giderler | D39: A2F01 | E39: =IFERROR(INDEX('QAR Kodları'!$B:$B,MATCH(D39,'QAR Kodları'!$A:$A,0)),"KOD BULUNAMADI") -> Receipts on account of financial intermediation except investment banking-bank charges, collection charges,lc charges, cancellation of forward | F39: Tam | G39: Finansal aracılık ücret/komisyonu. Saklama/varlık yönetimi ise A2F03. | H39: 23) Bankacılık ve finansal hizmetlerle ilgili Ücret, masraf, komisyon ödemeleri
A40: =B40&"-"&D40 -> 5761-A2F02 | B40: 5761 | C40: Yurtdışında yerleşik kişilerden finansal türev işlemleri ile ilgili alınan aracılık hizmetleri nedeniyle ödenen her türlü hizmet komisyonu ve benzeri giderler | D40: A2F02 | E40: =IFERROR(INDEX('QAR Kodları'!$B:$B,MATCH(D40,'QAR Kodları'!$A:$A,0)),"KOD BULUNAMADI") -> Receipts on account of investment banking services-brokerage, under writing commission etc | F40: Tam | G40: Türev işlem aracılık komisyonu. | H40: 23) Bankacılık ve finansal hizmetlerle ilgili Ücret, masraf, komisyon ödemeleri
A41: =B41&"-"&D41 -> 5762-A2F01 | B41: 5762 | C41: Yurtiçinde yerleşik kişilerden alınan finansal aracılık ve finansal nitelikli danışmanlık, saklama ve varlık yönetimi gibi hizmetler nedeniyle ödenen her türlü hizmet komisyonu ve benzeri giderler | D41: A2F01 | E41: =IFERROR(INDEX('QAR Kodları'!$B:$B,MATCH(D41,'QAR Kodları'!$A:$A,0)),"KOD BULUNAMADI") -> Receipts on account of financial intermediation except investment banking-bank charges, collection charges,lc charges, cancellation of forward | F41: Yakın | G41: Yurt içi yerleşikten alınan finansal hizmet; yurt dışına ödeniyorsa. | H41: 23) Bankacılık ve finansal hizmetlerle ilgili Ücret, masraf, komisyon ödemeleri
A42: =B42&"-"&D42 -> 5763-A2F02 | B42: 5763 | C42: Yurtiçinde yerleşik kişilerden finansal türev işlemleri ile ilgili alınan aracılık hizmetleri nedeniyle ödenen her türlü hizmet komisyonu ve benzeri giderler | D42: A2F02 | E42: =IFERROR(INDEX('QAR Kodları'!$B:$B,MATCH(D42,'QAR Kodları'!$A:$A,0)),"KOD BULUNAMADI") -> Receipts on account of investment banking services-brokerage, under writing commission etc | F42: Yakın | G42: Yurt içi yerleşikten türev aracılık hizmeti; yurt dışına ödeniyorsa. | H42: 23) Bankacılık ve finansal hizmetlerle ilgili Ücret, masraf, komisyon ödemeleri
A43: =B43&"-"&D43 -> 5770-A2R01 | B43: 5770 | C43: İmtiyaz ve ticari marka lisans giderleri | D43: A2R01 | E43: =IFERROR(INDEX('QAR Kodları'!$B:$B,MATCH(D43,'QAR Kodları'!$A:$A,0)),"KOD BULUNAMADI") -> Receipts on account of franchises services-use of patents, copy right trade marks, industrial processes, franchises etc. | F43: Tam | G43: İmtiyaz (franchise) ve ticari marka lisansı. | H43: 37) Hukuki danışmanlık, mahkeme, tazminat, bröve, marka tescil, üyelik/aidat işlemleri
A44: =B44&"-"&D44 -> 5771-A2R01 | B44: 5771 | C44: Telif, patent ve benzeri haklar nedeniyle ödenen bedeller | D44: A2R01 | E44: =IFERROR(INDEX('QAR Kodları'!$B:$B,MATCH(D44,'QAR Kodları'!$A:$A,0)),"KOD BULUNAMADI") -> Receipts on account of franchises services-use of patents, copy right trade marks, industrial processes, franchises etc. | F44: Tam | G44: Telif, patent ve benzeri hak bedeli. | H44: 28) Ticaret ve endüstri hizmetleri
A45: =B45&"-"&D45 -> 5772-A2R01 | B45: 5772 | C45: Araştırma ve geliştirme sonuçlarının kullanımına ilişkin lisans giderleri | D45: A2R01 | E45: =IFERROR(INDEX('QAR Kodları'!$B:$B,MATCH(D45,'QAR Kodları'!$A:$A,0)),"KOD BULUNAMADI") -> Receipts on account of franchises services-use of patents, copy right trade marks, industrial processes, franchises etc. | F45: Yakın | G45: Ar-Ge sonuçları kullanım lisansı. | H45: 28) Ticaret ve endüstri hizmetleri
A46: =B46&"-"&D46 -> 5773-A2R02 | B46: 5773 | C46: Bilgisayar yazılımlarının çoğaltılması ve/veya dağıtılmasına ilişkin lisans giderleri (Yazılımların toptan veya perakende alımı bilgisayar yazılım hizmetleri kodu altında gösterilecektir.) | D46: A2R02 | E46: =IFERROR(INDEX('QAR Kodları'!$B:$B,MATCH(D46,'QAR Kodları'!$A:$A,0)),"KOD BULUNAMADI") -> Receipts for use through licensing arrangements of produced originals or prototypes (such as manuscripts and films) | F46: Tam | G46: Orijinal/prototiplerin çoğaltma-dağıtım lisansı. | H46: 28) Ticaret ve endüstri hizmetleri
A47: =B47&"-"&D47 -> 5774-A2R02 | B47: 5774 | C47: Görsel-işitsel (audio-visual) ve ilgili ürünlerin çoğaltılması ve/veya dağıtılmasına ilişkin lisans giderleri | D47: A2R02 | E47: =IFERROR(INDEX('QAR Kodları'!$B:$B,MATCH(D47,'QAR Kodları'!$A:$A,0)),"KOD BULUNAMADI") -> Receipts for use through licensing arrangements of produced originals or prototypes (such as manuscripts and films) | F47: Tam | G47: Orijinal/prototiplerin çoğaltma-dağıtım lisansı. | H47: 28) Ticaret ve endüstri hizmetleri
A48: =B48&"-"&D48 -> 5775-A2R02 | B48: 5775 | C48: Görsel-işitsel (audio-visual) ve ilgili ürünler dışındaki ürünlerin çoğaltılması ve/veya dağıtılmasına ilişkin lisans giderleri | D48: A2R02 | E48: =IFERROR(INDEX('QAR Kodları'!$B:$B,MATCH(D48,'QAR Kodları'!$A:$A,0)),"KOD BULUNAMADI") -> Receipts for use through licensing arrangements of produced originals or prototypes (such as manuscripts and films) | F48: Tam | G48: Orijinal/prototiplerin çoğaltma-dağıtım lisansı. | H48: 28) Ticaret ve endüstri hizmetleri
A49: =B49&"-"&D49 -> 5780-A2K03 | B49: 5780 | C49: Telekomünikasyon hizmetleri: Yurtdışında yerleşik kişilerden sağlanan ses,görüntü, veri ve diğer bilgilerin telefon, teleks, telgraf, radyo ve televizyon uydusu kablo, elektronik posta vb. ile iletilmesi gibi hizmetler nedeniyle ödenen bedeller (Taşınan bilgilerin bedeli hariç tutulacaktır. İş ağı hizmetleri, telekonferans ve destek hizmetleri, mobil telekomünikasyon hizmetleri, internet altyapı hizmetleri, internet erişimi sağlanması dahil çevrimiçi erişim hizmetleri bu kod altında bildirilecektir) | D49: A2K03 | E49: =IFERROR(INDEX('QAR Kodları'!$B:$B,MATCH(D49,'QAR Kodları'!$A:$A,0)),"KOD BULUNAMADI") -> Receipts on account of settlement of claims for telecommunication services | F49: Tam | H49: 42) Telekomünikasyon Hizmetleri
A50: =B50&"-"&D50 -> 5781-A2E02 | B50: 5781 | C50: Bilgisayar yazılım hizmetleri: Yurtiçinde yerleşik kişiler için yazılım geliştirilmesi ve ilgili kullanım lisansları, yazılım sistemleri ve uygulamaları için orijinallerin (asılların) ve mülkiyet haklarının alımı vb. gibi yazılım hizmetleri nedeniyle ödenen bedeller | D50: A2E02 | E50: =IFERROR(INDEX('QAR Kodları'!$B:$B,MATCH(D50,'QAR Kodları'!$A:$A,0)),"KOD BULUNAMADI") -> Receipts on account of software implementation | F50: Tam | H50: 43) Bilgisayar ve Bilgi Hizmetleri
A51: =B51&"-"&D51 -> 5782-A2E04 | B51: 5782 | C51: Diğer bilgisayar hizmetleri: Yurtdışında yerleşik kişilerden bilgi işlemle ilgili olarak alınan danışmanlık, bakım, onarım sistem programlaması ve tasarımı hizmetleri (web sitesi tasarım ve kurulum hizmetleri dahil) ile veri kurtarma, veri işleme gibi bilgisayar donanım ve yazılım hizmetleri nedeniyle ödenen bedeller | D51: A2E04 | E51: =IFERROR(INDEX('QAR Kodları'!$B:$B,MATCH(D51,'QAR Kodları'!$A:$A,0)),"KOD BULUNAMADI") -> Receipts on account of repair and maintenance of computer and software | F51: Yakın | G51: Bakım/onarım. Danışmanlık ağırlıklıysa A2E01. | H51: 43) Bilgisayar ve Bilgi Hizmetleri
A52: =B52&"-"&D52 -> 5783-A2E05 | B52: 5783 | C52: Haber ajansı hizmetleri: Yurtdışında yerleşik medya kuruluşlarından haber, fotoğraf ve makale sağlanması dolayısıyla ödenen bedeller | D52: A2E05 | E52: =IFERROR(INDEX('QAR Kodları'!$B:$B,MATCH(D52,'QAR Kodları'!$A:$A,0)),"KOD BULUNAMADI") -> Receipts on account of provision of news agency services | F52: Tam | H52: 43) Bilgisayar ve Bilgi Hizmetleri
A53: =B53&"-"&D53 -> 5784-A2E06 | B53: 5784 | C53: Diğer bilgi hizmetleri: Yurtdışında yerleşik kişilerden alınan veri tabanı, veri saklama, veri dağıtım ve internet tarama hizmetleri ile gazete ve süreli yayınlara, posta, elektronik dağıtım veya diğer yollarla toplu olmayan doğrudan abonelikler nedeniyle ödenen bedeller | D53: A2E06 | E53: =IFERROR(INDEX('QAR Kodları'!$B:$B,MATCH(D53,'QAR Kodları'!$A:$A,0)),"KOD BULUNAMADI") -> Receipts on account of other information services-subscription to newspapers, periodicals etc. | F53: Yakın | G53: Abonelik/bilgi hizmeti. Veri tabanı/veri işleme ise A2E03. | H53: 43) Bilgisayar ve Bilgi Hizmetleri
A54: =B54&"-"&D54 -> 5790-A2J08 | B54: 5790 | C54: Araştırma geliştirme hizmetleri (Araştırma ve geliştirme faaliyetleri sonucu ortaya çıkan patent gibi ilgili fikri mülkiyet haklarının alımı nedeniyle ödenen bedeller dahil) | D54: A2J08 | E54: =IFERROR(INDEX('QAR Kodları'!$B:$B,MATCH(D54,'QAR Kodları'!$A:$A,0)),"KOD BULUNAMADI") -> Receipts towards research & development services | F54: Tam | H54: 28) Ticaret ve endüstri hizmetleri
A55: =B55&"-"&D55 -> 5791-A2J04 | B55: 5791 | C55: Hukuk hizmetleri | D55: A2J04 | E55: =IFERROR(INDEX('QAR Kodları'!$B:$B,MATCH(D55,'QAR Kodları'!$A:$A,0)),"KOD BULUNAMADI") -> Receipts towards legal services | F55: Tam | H55: 37) Hukuki danışmanlık, mahkeme, tazminat, bröve, marka tescil, üyelik/aidat işlemleri
A56: =B56&"-"&D56 -> 5792-A2J05 | B56: 5792 | C56: Muhasebe, gözetim, defter tutma ve vergi danışmanlığı hizmetleri | D56: A2J05 | E56: =IFERROR(INDEX('QAR Kodları'!$B:$B,MATCH(D56,'QAR Kodları'!$A:$A,0)),"KOD BULUNAMADI") -> Receipts for providing accounting,auditing,book keeping and tax consulting services | F56: Tam | H56: 28) Ticaret ve endüstri hizmetleri
A57: =B57&"-"&D57 -> 5793-A2J06 | B57: 5793 | C57: İşletme ve yönetim danışmanlığı ile halkla ilişkiler hizmetleri | D57: A2J06 | E57: =IFERROR(INDEX('QAR Kodları'!$B:$B,MATCH(D57,'QAR Kodları'!$A:$A,0)),"KOD BULUNAMADI") -> Receipts for provision of business and management consultancy and public relations services | F57: Tam | H57: 28) Ticaret ve endüstri hizmetleri
A58: =B58&"-"&D58 -> 5794-A2J07 | B58: 5794 | C58: Reklam, pazarlama, pazar ve piyasa araştırma hizmetleri ile yurtdışında düzenlenen kongre, fuar ve sergiler nedeniyle ödenen bedeller | D58: A2J07 | E58: =IFERROR(INDEX('QAR Kodları'!$B:$B,MATCH(D58,'QAR Kodları'!$A:$A,0)),"KOD BULUNAMADI") -> Receipts for advertising, trade fair, market research and public opinion polling service | F58: Tam | H58: 29) Dış ticaret hizmetleri
A59: =B59&"-"&D59 -> 5795-A2J09 | B59: 5795 | C59: Mimari hizmetler, mühendislik hizmetleri ile bilimsel ve diğer teknik hizmetler | D59: A2J09 | E59: =IFERROR(INDEX('QAR Kodları'!$B:$B,MATCH(D59,'QAR Kodları'!$A:$A,0)),"KOD BULUNAMADI") -> Receipts for providing architectural engineering and other technical services | F59: Tam | H59: 28) Ticaret ve endüstri hizmetleri
A60: =B60&"-"&D60 -> 5796-A2J13 | B60: 5796 | C60: Atık bertaraf, geri kazanım ve arındırma hizmetleri | D60: A2J13 | E60: =IFERROR(INDEX('QAR Kodları'!$B:$B,MATCH(D60,'QAR Kodları'!$A:$A,0)),"KOD BULUNAMADI") -> Inward remit. Towards environmental services | F60: Tam | G60: Atık/arıtma = çevre hizmetleri. | H60: 28) Ticaret ve endüstri hizmetleri
A61: =B61&"-"&D61 -> 5797-A2J10 | B61: 5797 | C61: Tarım, ormancılık ve balıkçılıkla dolaylı olarak ilgili olan hizmetler | D61: A2J10 | E61: =IFERROR(INDEX('QAR Kodları'!$B:$B,MATCH(D61,'QAR Kodları'!$A:$A,0)),"KOD BULUNAMADI") -> Receipts for agricultural, mining and onsite processing services protection against insects & disease, increasing of harvest yields, forestry s | F61: Tam | H61: 28) Ticaret ve endüstri hizmetleri
A62: =B62&"-"&D62 -> 5798-A2J10 | B62: 5798 | C62: Madencilik, petrol ve doğalgaz çıkartılmasıyla dolaylı olarak ilgili olan hizmetler | D62: A2J10 | E62: =IFERROR(INDEX('QAR Kodları'!$B:$B,MATCH(D62,'QAR Kodları'!$A:$A,0)),"KOD BULUNAMADI") -> Receipts for agricultural, mining and onsite processing services protection against insects & disease, increasing of harvest yields, forestry s | F62: Tam | H62: 28) Ticaret ve endüstri hizmetleri
A63: =B63&"-"&D63 -> 5799-A2J03 | B63: 5799 | C63: Operasyonel kiralama giderleri: Yurtdışında yerleşik kişilerden mürettebatsız olarak kısa süreli taşıt, makina ve ekipman kiralanması nedeniyle ödenen bedeller (Mürettebatıyla birlikte kısa süreli taşıt kiralanması nedeniyle ödenen bedeller Taşımacılık/Yolcu Taşımacılığı Hizmetlerinde gösterilecektir) | D63: A2J03 | E63: =IFERROR(INDEX('QAR Kodları'!$B:$B,MATCH(D63,'QAR Kodları'!$A:$A,0)),"KOD BULUNAMADI") -> Receipts towards dry operational leasing services (other than financial leasing and without operating crew) including charter hire | F63: Tam | G63: Mürettebatsız operasyonel kiralama. | H63: 28) Ticaret ve endüstri hizmetleri
A64: =B64&"-"&D64 -> 5800-A2J11 | B64: 5800 | C64: Yabancı sermaye şirketleri arasında gerçekleşen ve diğer hizmet sınıflamalarına girmeyen hizmetler (Yabancı sermaye konusu yurtdışındaki şube, iştirak ve bağlı ortaklıkların genel yönetim ve gider harcamaları için ana ortak tarafından gönderilen tutarlar) | D64: A2J11 | E64: =IFERROR(INDEX('QAR Kodları'!$B:$B,MATCH(D64,'QAR Kodları'!$A:$A,0)),"KOD BULUNAMADI") -> Inward remittance for maintenance of offices in Qatar | F64: Yakın | G64: Grup şirketleri arası / ofis giderleri. | H64: 28) Ticaret ve endüstri hizmetleri
A65: =B65&"-"&D65 -> 5801-A2J19 | B65: 5801 | C65: Gayrimenkul yönetim hizmetleri | D65: A2J19 | E65: =IFERROR(INDEX('QAR Kodları'!$B:$B,MATCH(D65,'QAR Kodları'!$A:$A,0)),"KOD BULUNAMADI") -> Receipts for other services not included elsewhere | F65: Genel / En yakın | G65: QAR'da ayrı kod yok; diğer hizmetler. | H65: 28) Ticaret ve endüstri hizmetleri
A66: =B66&"-"&D66 -> 5802-A2J19 | B66: 5802 | C66: Çeviri hizmetleri | D66: A2J19 | E66: =IFERROR(INDEX('QAR Kodları'!$B:$B,MATCH(D66,'QAR Kodları'!$A:$A,0)),"KOD BULUNAMADI") -> Receipts for other services not included elsewhere | F66: Genel / En yakın | G66: QAR'da ayrı kod yok; diğer hizmetler. | H66: 28) Ticaret ve endüstri hizmetleri
A67: =B67&"-"&D67 -> 5803-A2J19 | B67: 5803 | C67: İnsan kaynakları, iş bulma ve istihdam hizmetleri | D67: A2J19 | E67: =IFERROR(INDEX('QAR Kodları'!$B:$B,MATCH(D67,'QAR Kodları'!$A:$A,0)),"KOD BULUNAMADI") -> Receipts for other services not included elsewhere | F67: Genel / En yakın | G67: QAR'da ayrı kod yok; diğer hizmetler. | H67: 28) Ticaret ve endüstri hizmetleri
A68: =B68&"-"&D68 -> 5805-A2J19 | B68: 5805 | C68: TPKK hakkında 32 Sayılı Karara uygun olarak yurtiçine döviz olarak verilen döviz kredisi karşılığında görünmeyen işlemlere ilişkin yurtdışına yapılan transferler | D68: A2J19 | E68: =IFERROR(INDEX('QAR Kodları'!$B:$B,MATCH(D68,'QAR Kodları'!$A:$A,0)),"KOD BULUNAMADI") -> Receipts for other services not included elsewhere | F68: Genel / En yakın | G68: Döviz kredisi karşılığı görünmeyen işlem transferi; içeriğe göre değişir. | H68: 29) Dış ticaret hizmetleri
A69: =B69&"-"&D69 -> 5807-A2J02 | B69: 5807 | C69: Komisyonculuk hizmet gideri: Mal ve hizmet işlemlerine ilişkin olarak yurtdışında yerleşik aracılar tarafından alınan komisyonlar, yurtiçine yapılan komisyonculuk ile (mümessillik, ticari mümessillik, ticari vekillik, ticari işler tellallığı, simsarlık, acentelik, distribütörlük ve benzeri) Türkiye ve yabancı bir ülke arasındaki ticari bağlantıların sağlanmasından dolayı ödenen bedeller | D69: A2J02 | E69: =IFERROR(INDEX('QAR Kodları'!$B:$B,MATCH(D69,'QAR Kodları'!$A:$A,0)),"KOD BULUNAMADI") -> Trade related services - commission on exports/imports | F69: Tam | G69: İhracat/ithalat komisyonu. | H69: 29) Dış ticaret hizmetleri
A70: =B70&"-"&D70 -> 5810-A2H01 | B70: 5810 | C70: Görsel-İşitsel hizmetler: Bant, video-kaset, disk veya elektronik ortamdaki sinema filmleri, radyo ve televizyon programları ve müzik kayıtlarının yapımına ilişkin hizmetler ile görsel-işitsel ve ilgili ürünlerin kiralanması, şifreli televizyon kanallarına erişim ücretleri nedeniyle ödenen bedeller (Eserlerin orijinalleri, müzikal kayıtlar ve filmlerin alımı nedeniyle ödenen bedeller de bu kod altında bildirilecektir) | D70: A2H01 | E70: =IFERROR(INDEX('QAR Kodları'!$B:$B,MATCH(D70,'QAR Kodları'!$A:$A,0)),"KOD BULUNAMADI") -> Receipts for audio-visual and related services services and associated fees related to production of motion pictures,rentals,fees received b | F70: Tam | H70: 32) Görsel ve işitsel hizmetler
A71: =B71&"-"&D71 -> 5811-A2H01 | B71: 5811 | C71: Sanatçılar (aktörler, müzisyenler, dansçılar vb.), yazarlar, besteciler ve heykeltraşlar tarafından sağlanan hizmetler ile sahne sanatları ve diğer canlı eğlence etkinliklerinin kaydı, tanıtım ve sunumu nedeniyle ödenen bedeller | D71: A2H01 | E71: =IFERROR(INDEX('QAR Kodları'!$B:$B,MATCH(D71,'QAR Kodları'!$A:$A,0)),"KOD BULUNAMADI") -> Receipts for audio-visual and related services services and associated fees related to production of motion pictures,rentals,fees received b | F71: Tam | H71: 32) Görsel ve işitsel hizmetler
A72: =B72&"-"&D72 -> 5812-A2H02 | B72: 5812 | C72: Diğer kişisel, kültürel ve eğitsel hizmetler: Bu kod altında uzaktan televizyon ya da internet aracılığıyla sağlanan sağlık ve eğitim hizmetleri, müze ve kütüphanecilik hizmetleri gibi kültürel hizmetler ile sportif hizmetler bildirilecektir (“5730 - Seyahat Giderleri” kodu altında bildirilen, yurtdışına eğitim ve tedavi amacıyla giden yurtiçinde yerleşik kişilerin yurtdışındaki harcamaları dahil edilmeyecektir) | D72: A2H02 | E72: =IFERROR(INDEX('QAR Kodları'!$B:$B,MATCH(D72,'QAR Kodları'!$A:$A,0)),"KOD BULUNAMADI") -> Receipts towards personal cultural services such as those related to museums libraries archives and sporting activities also includes fees | F72: Yakın | H72: 32) Görsel ve işitsel hizmetler
A73: =B73&"-"&D73 -> 5813-A2H02 | B73: 5813 | C73: Spor ödülleri ve yarışma kazançları | D73: A2H02 | E73: =IFERROR(INDEX('QAR Kodları'!$B:$B,MATCH(D73,'QAR Kodları'!$A:$A,0)),"KOD BULUNAMADI") -> Receipts towards personal cultural services such as those related to museums libraries archives and sporting activities also includes fees | F73: Yakın | H73: 32) Görsel ve işitsel hizmetler
A74: =B74&"-"&D74 -> 5830-A2G07 | B74: 5830 | C74: Yurtiçinde yerleşik kişilerin Türkiyedeki yabancı elçilik, konsolosluk, askeri ve sivil temsilcilikler ile gerçekleştirdikleri hizmetlere ilişkin işlemler nedeniyle yaptıkları ödemeler | D74: A2G07 | E74: =IFERROR(INDEX('QAR Kodları'!$B:$B,MATCH(D74,'QAR Kodları'!$A:$A,0)),"KOD BULUNAMADI") -> incoming remittances on account of government services | F74: Yakın | G74: Katar temsilciliğine ödenen resmi hizmet bedeli (vize vb.). | H74: 36) Kamu gelir ve giderleri
A75: =B75&"-"&D75 -> 5831-A2G01 | B75: 5831 | C75: T.C. elçilik, konsolosluk, askeri ve sivil temsilciliklerinin, ofis ve personel ihtiyaçları için bulundukları ülkeden sağladıkları mal ve hizmetler nedeniyle yaptıkları ödemeler (Türkiye Cumhuriyeti yabancı temsilciliklerinin Türk tabiiyetli personeli ve yakınları Türkiyenin yerleşiği kabul edildiğinden, söz konusu kişilerin bulundukları ülkelerde yaptıkları harcamalar da bu kod altında bildirilecektir) | D75: A2G01 | E75: =IFERROR(INDEX('QAR Kodları'!$B:$B,MATCH(D75,'QAR Kodları'!$A:$A,0)),"KOD BULUNAMADI") -> Inward remittance received for maintenance of foreign embassies in Qatar | F75: Tam | G75: T.C. temsilciliklerinin Katar'daki ofis/personel giderleri. | H75: 36) Kamu gelir ve giderleri
A76: =B76&"-"&D76 -> 5832-A2G07 | B76: 5832 | C76: Diğer resmi hizmet giderleri | D76: A2G07 | E76: =IFERROR(INDEX('QAR Kodları'!$B:$B,MATCH(D76,'QAR Kodları'!$A:$A,0)),"KOD BULUNAMADI") -> incoming remittances on account of government services | F76: Yakın | H76: 36) Kamu gelir ve giderleri
A77: =B77&"-"&D77 -> 5840-A2J19 | B77: 5840 | C77: İşlem gören mallar nedeniyle ödenen bedeller (işleme tabi tutma, tamamlama ve benzerleri dahil) | D77: A2J19 | E77: =IFERROR(INDEX('QAR Kodları'!$B:$B,MATCH(D77,'QAR Kodları'!$A:$A,0)),"KOD BULUNAMADI") -> Receipts for other services not included elsewhere | F77: Genel / En yakın | G77: İşleme hizmetleri; QAR'da ayrı kod yok. | H77: 28) Ticaret ve endüstri hizmetleri
A78: =B78&"-"&D78 -> 5850-A2J19 | B78: 5850 | C78: Yurtiçinde yerleşik kilere ait mallar ile deniz, hava ve kara taşıtlarının yurtdışında tamir ve bakımına ilişkin giderler (Söz konusu taşıtlara ilişkin temizlik hizmetleri ile sabit yapılar, yollar, köprüler vb. ile bilgisayarlara ilişkin tamir ve bakım hizmetleri hariç tutulacaktır.) | D78: A2J19 | E78: =IFERROR(INDEX('QAR Kodları'!$B:$B,MATCH(D78,'QAR Kodları'!$A:$A,0)),"KOD BULUNAMADI") -> Receipts for other services not included elsewhere | F78: Genel / En yakın | G78: Tamir-bakım (bilgisayar dışı); QAR'da yalnız bilgisayar bakımı (A2E04) var. | H78: 28) Ticaret ve endüstri hizmetleri
A79: =B79&"-"&D79 -> 5860-A3A05 | B79: 5860 | C79: Bankacılık işlemleri nedeniyle yurtdışı cari hesaplara ödenen faizler | D79: A3A05 | E79: =IFERROR(INDEX('QAR Kodları'!$B:$B,MATCH(D79,'QAR Kodları'!$A:$A,0)),"KOD BULUNAMADI") -> Inwards remittance towards interest receipts of ads on their own account (on investments) | F79: Yakın | G79: Bankacılık işlemleri nedeniyle yurt dışı cari hesaplara faiz. | H79: 16) Depo/Repo/Ters Repo İşlemleri
A80: =B80&"-"&D80 -> 5861-A3A05 | B80: 5861 | C80: Yurtdışında yerleşik kişi, kuruluş ve bankalarca açılmış döviz hesaplarına ödenen faizler | D80: A3A05 | E80: =IFERROR(INDEX('QAR Kodları'!$B:$B,MATCH(D80,'QAR Kodları'!$A:$A,0)),"KOD BULUNAMADI") -> Inwards remittance towards interest receipts of ads on their own account (on investments) | F80: Genel / En yakın | G80: Yurt dışı yerleşik döviz hesaplarına mevduat faizi; QAR'da mevduat faizi kodu yok. | H80: 16) Depo/Repo/Ters Repo İşlemleri
A81: =B81&"-"&D81 -> 5862-A3A03 | B81: 5862 | C81: Kabul kredili ve akreditifli (vadeli) ithalat işleminde, ithalat bedelinin ihracatçıya, vesaikin muhabire verilmesinden itibaren 365 güne kadarki bir tarihte ödenecek olması dolayısıyla oluşan kısa vadeli ithalat borçlarına ilişkin faiz ödemeleri | D81: A3A03 | E81: =IFERROR(INDEX('QAR Kodları'!$B:$B,MATCH(D81,'QAR Kodları'!$A:$A,0)),"KOD BULUNAMADI") -> Inwards remittance towards interest on loans extended to non residents (st/mt/lt loans) | F81: Yakın | G81: Vadeli ithalat (kabul kredili/akreditifli) faizi. | H81: 40) Kredi Faiz Ödemesi
A82: =B82&"-"&D82 -> 5880-A4B07 | B82: 5880 | C82: Bir seneden daha kısa bir süre için yurtiçinde çalışmakta olan yurtdışında yerleşik kişilere yurtiçinde yerleşik işveren tarafından ödenen ücret ve maaşlar (Bir yıldan fazla süredir yurtiçinde ikamet eden ve dolayısıyla yurtiçinde yerleşik olan işçilere ödenen ücret ve maaşlar hariç) | D82: A4B07 | E82: =IFERROR(INDEX('QAR Kodları'!$B:$B,MATCH(D82,'QAR Kodları'!$A:$A,0)),"KOD BULUNAMADI") -> Compensation of employees (short term) | F82: Tam | G82: Kısa dönemli çalışan ücreti. | H82: 35) Kişisel gelir ve harcamalar, ücret ve emeklilik ödemeleri
A83: =B83&"-"&D83 -> 5881-A4B07 | B83: 5881 | C83: Türkiyenin dış temsilciliklerinde çalışan yabancı tabiiyetli personele söz konusu temsilciliklerimizce yapılan ücret ve maaş ödemeleri | D83: A4B07 | E83: =IFERROR(INDEX('QAR Kodları'!$B:$B,MATCH(D83,'QAR Kodları'!$A:$A,0)),"KOD BULUNAMADI") -> Compensation of employees (short term) | F83: Tam | G83: Kısa dönemli çalışan ücreti. | H83: 35) Kişisel gelir ve harcamalar, ücret ve emeklilik ödemeleri
A84: =B84&"-"&D84 -> 5900-A4B04 | B84: 5900 | C84: Yurtdışına hibe şeklinde gönderilen dövizler | D84: A4B04 | E84: =IFERROR(INDEX('QAR Kodları'!$B:$B,MATCH(D84,'QAR Kodları'!$A:$A,0)),"KOD BULUNAMADI") -> Inward remittance towards grants and donations to government and charitable institution established by the governments | F84: Yakın | G84: Hibe / resmi transfer. | H84: 36) Kamu gelir ve giderleri
A85: =B85&"-"&D85 -> 5901-A4B04 | B85: 5901 | C85: Nato-Enfrastrüktür kapsamında gönderilen hibeler | D85: A4B04 | E85: =IFERROR(INDEX('QAR Kodları'!$B:$B,MATCH(D85,'QAR Kodları'!$A:$A,0)),"KOD BULUNAMADI") -> Inward remittance towards grants and donations to government and charitable institution established by the governments | F85: Yakın | G85: Hibe / resmi transfer. | H85: 36) Kamu gelir ve giderleri
A86: =B86&"-"&D86 -> 5902-A4B02 | B86: 5902 | C86: Yurtdışında yerleşik kişilere yapılan sosyal güvenlik ödemeleri ve diğer kanuni ödemeler | D86: A4B02 | E86: =IFERROR(INDEX('QAR Kodları'!$B:$B,MATCH(D86,'QAR Kodları'!$A:$A,0)),"KOD BULUNAMADI") -> Inward remittance towards personal gifts and donations | F86: Genel / En yakın | G86: Sosyal güvenlik ödemesi; QAR'da ayrı kod yok. | H86: 36) Kamu gelir ve giderleri
A87: =B87&"-"&D87 -> 5903-A4B06 | B87: 5903 | C87: Katma değer vergisi için yapılan döviz iadeleri (Yurtdışında yerleşik kişilerin yurtiçindeki turistik seyahatlerinde satın aldıkları mallara ilişkin Katma Değer Vergisi iadeleri dahil) | D87: A4B06 | E87: =IFERROR(INDEX('QAR Kodları'!$B:$B,MATCH(D87,'QAR Kodları'!$A:$A,0)),"KOD BULUNAMADI") -> Receipts towards receipts/refund of taxes | F87: Tam | G87: KDV iadesi. | H87: 36) Kamu gelir ve giderleri
A88: =B88&"-"&D88 -> 5904-A4B04 | B88: 5904 | C88: Diğer resmi transferler | D88: A4B04 | E88: =IFERROR(INDEX('QAR Kodları'!$B:$B,MATCH(D88,'QAR Kodları'!$A:$A,0)),"KOD BULUNAMADI") -> Inward remittance towards grants and donations to government and charitable institution established by the governments | F88: Yakın | G88: Hibe / resmi transfer. | H88: 36) Kamu gelir ve giderleri
... A98: =B98&"-"&D98 -> 5922-A6C18 | B98: 5922 | C98: Genel Hükümet hariç yurtiçinde yerleşik kişiler tarafından yurtdışında yerleşik kişilere sağlanan nakdi yatırım hibeleri | D98: A6C18 | E98: =IFERROR(INDEX('QAR Kodları'!$B:$B,MATCH(D98,'QAR Kodları'!$A:$A,0)),"KOD BULUNAMADI") -> Other capital receipts (not included else where) | F98: Genel / En yakın | G98: Özel kesim yatırım hibesi (sermaye transferi). | H98: 35) Kişisel gelir ve harcamalar, ücret ve emeklilik ödemeleri
A99: =B99&"-"&D99 -> T5930-A6C18 | B99: T5930 | C99: Yurtiçinde yerleşik alacaklı kuruluş tarafından borcun affedilmesi | D99: A6C18 | E99: =IFERROR(INDEX('QAR Kodları'!$B:$B,MATCH(D99,'QAR Kodları'!$A:$A,0)),"KOD BULUNAMADI") -> Other capital receipts (not included else where) | F99: Genel / En yakın | G99: Borç affı; nakit akımı yok, sermaye transferi niteliğinde. | H99: 24) İade işlemi
A100: =B100&"-"&D100 -> 6051-A6C11 | B100: 6051 | C100: Bankalarca yurtdışında yerleşik ticari bankalardan sağlanan orta-uzun vadeli kredi anapara ödemesi | D100: A6C11 | E100: =IFERROR(INDEX('QAR Kodları'!$B:$B,MATCH(D100,'QAR Kodları'!$A:$A,0)),"KOD BULUNAMADI") -> Repayment of loans extended to non-residents | F100: Tam | G100: Yurt dışından alınan kredinin anapara geri ödemesi. | H100: 11) Kredi Anapara Ödemesi
A101: =B101&"-"&D101 -> 6052-A3A03 | B101: 6052 | C101: Bankalarca yurdışında yerleşik ticari bankalardan sağlanan orta-uzun vadeli kredi faiz ödemesi | D101: A3A03 | E101: =IFERROR(INDEX('QAR Kodları'!$B:$B,MATCH(D101,'QAR Kodları'!$A:$A,0)),"KOD BULUNAMADI") -> Inwards remittance towards interest on loans extended to non residents (st/mt/lt loans) | F101: Tam | G101: Kredi faizi. | H101: 40) Kredi Faiz Ödemesi
A102: =B102&"-"&D102 -> 6053-A6C11 | B102: 6053 | C102: Bankalarca yurtdışında yerleşik ticari bankalardan sağlanan kısa vadeli kredi anapara ödemesi | D102: A6C11 | E102: =IFERROR(INDEX('QAR Kodları'!$B:$B,MATCH(D102,'QAR Kodları'!$A:$A,0)),"KOD BULUNAMADI") -> Repayment of loans extended to non-residents | F102: Tam | G102: Yurt dışından alınan kredinin anapara geri ödemesi. | H102: 11) Kredi Anapara Ödemesi
A103: =B103&"-"&D103 -> 6054-A3A03 | B103: 6054 | C103: Bankalarca yurtdışında yerleşik ticari bankalardan sağlanan kısa vadeli kredi faiz ödemesi | D103: A3A03 | E103: =IFERROR(INDEX('QAR Kodları'!$B:$B,MATCH(D103,'QAR Kodları'!$A:$A,0)),"KOD BULUNAMADI") -> Inwards remittance towards interest on loans extended to non residents (st/mt/lt loans) | F103: Tam | G103: Kredi faizi. | H103: 40) Kredi Faiz Ödemesi
A104: =B104&"-"&D104 -> 6055-A6C11 | B104: 6055 | C104: Prefinansman ihracat amacı ile bankalarca, özel kesimin talebi üzerine, yurtdışında yerleşik ticari kuruluşlardan sağlanan kısa vadeli kredi anapara geri ödemesi | D104: A6C11 | E104: =IFERROR(INDEX('QAR Kodları'!$B:$B,MATCH(D104,'QAR Kodları'!$A:$A,0)),"KOD BULUNAMADI") -> Repayment of loans extended to non-residents | F104: Tam | G104: Yurt dışından alınan kredinin anapara geri ödemesi. | H104: 11) Kredi Anapara Ödemesi
A105: =B105&"-"&D105 -> 6056-A3A03 | B105: 6056 | C105: Prefinansman ihracat amacı ile bankalarca, özel kesimin talebi üzerine, yurtdışında yerleşik ticari kuruluşlardan sağlanan kısa vadeli kredi faiz ödemesi | D105: A3A03 | E105: =IFERROR(INDEX('QAR Kodları'!$B:$B,MATCH(D105,'QAR Kodları'!$A:$A,0)),"KOD BULUNAMADI") -> Inwards remittance towards interest on loans extended to non residents (st/mt/lt loans) | F105: Tam | G105: Kredi faizi. | H105: 40) Kredi Faiz Ödemesi
A106: =B106&"-"&D106 -> 6061-A6C11 | B106: 6061 | C106: Bankalarca yurtdışında yerleşik ticari kuruluşlardan sağlanan orta-uzun vadeli kredi anapara ödemesi | D106: A6C11 | E106: =IFERROR(INDEX('QAR Kodları'!$B:$B,MATCH(D106,'QAR Kodları'!$A:$A,0)),"KOD BULUNAMADI") -> Repayment of loans extended to non-residents | F106: Tam | G106: Yurt dışından alınan kredinin anapara geri ödemesi. | H106: 11) Kredi Anapara Ödemesi
A107: =B107&"-"&D107 -> 6062-A3A03 | B107: 6062 | C107: Bankalarca yurtdışında yerleşik ticari kuruluşlardan sağlanan orta-uzun vadeli kredi faiz ödemesi | D107: A3A03 | E107: =IFERROR(INDEX('QAR Kodları'!$B:$B,MATCH(D107,'QAR Kodları'!$A:$A,0)),"KOD BULUNAMADI") -> Inwards remittance towards interest on loans extended to non residents (st/mt/lt loans) | F107: Tam | G107: Kredi faizi. | H107: 40) Kredi Faiz Ödemesi
A108: =B108&"-"&D108 -> 6063-A6C11 | B108: 6063 | C108: Bankalarca yurtdışında yerleşik ticari kuruluşlardan sağlanan kısa vadeli kredi anapara ödemesi | D108: A6C11 | E108: =IFERROR(INDEX('QAR Kodları'!$B:$B,MATCH(D108,'QAR Kodları'!$A:$A,0)),"KOD BULUNAMADI") -> Repayment of loans extended to non-residents | F108: Tam | G108: Yurt dışından alınan kredinin anapara geri ödemesi. | H108: 11) Kredi Anapara Ödemesi
A109: =B109&"-"&D109 -> 6064-A3A03 | B109: 6064 | C109: Bankalarca yurtdışında yerleşik ticari kuruluşlardan sağlanan kısa vadeli kredi faiz ödemesi | D109: A3A03 | E109: =IFERROR(INDEX('QAR Kodları'!$B:$B,MATCH(D109,'QAR Kodları'!$A:$A,0)),"KOD BULUNAMADI") -> Inwards remittance towards interest on loans extended to non residents (st/mt/lt loans) | F109: Tam | G109: Kredi faizi. | H109: 40) Kredi Faiz Ödemesi
A110: =B110&"-"&D110 -> 6071-A6B02 | B110: 6071 | C110: Ticari bankalarca döviz üzerinden düzenlenerek, yurtdışına ihraç edilmiş uzun vadeli (365 günü aşan) tahvil, ticari senet (commercial paper) ve benzeri kıymetli evrak tasfiyesi nedeniyle yurtdışına transfer edilen bedeller | D110: A6B02 | E110: =IFERROR(INDEX('QAR Kodları'!$B:$B,MATCH(D110,'QAR Kodları'!$A:$A,0)),"KOD BULUNAMADI") -> Repatriation of Qatari investment abroad in debt securities | F110: Tam | G110: Türk ihraççı tahvil/CP itfası; Katarlı yatırımcıya anapara dönüşü. | H110: 13) Menkul Kıymet Anapara Ödemesi
A111: =B111&"-"&D111 -> 6072-A3A04 | B111: 6072 | C111: Ticari bankalarca döviz üzerinden düzenlenerek, yurtdışına ihraç edilmiş uzun vadeli (365 günü aşan) tahvil, ticari senet (commercial paper) ve benzeri kıymetli evrak nedeniyle yurtdışına transfer edilen faiz ve benzeri ödemeler | D111: A3A04 | E111: =IFERROR(INDEX('QAR Kodları'!$B:$B,MATCH(D111,'QAR Kodları'!$A:$A,0)),"KOD BULUNAMADI") -> Inwards remittance of interest on debt securities debentures/bonds/frns etc | F111: Tam | G111: Tahvil/bono faiz-kupon ödemesi. | H111: 41) Menkul Kıymet Kupon/Faiz Ödemesi
... A263: =B263&"-"&D263 -> 7630-A6C18 | B263: 7630 | C263: Bankanın kendi adına yurtdışı yerleşik kişiler ile gerçekleştirdiği forward, futures ve swap işlemlerinden işlemlerinden elde ettiği zarar | D263: A6C18 | E263: =IFERROR(INDEX('QAR Kodları'!$B:$B,MATCH(D263,'QAR Kodları'!$A:$A,0)),"KOD BULUNAMADI") -> Other capital receipts (not included else where) | F263: Genel / En yakın | G263: Türev işlem kâr/zarar ödemesi; QAR'da türev kodu yok. Forward iptali ise A2F01 de düşünülebilir. | H263: 8) Teminat İşlemleri (Finansal Ürün İlişkili)
A264: =B264&"-"&D264 -> T7630-A6C18 | B264: T7630 | C264: Bankanın kendi adına yurtdışı yerleşik kişiler ile gerçekleştirdiği forward, futures ve swap işlemleri için, muhabir hesaplarına yansımayan ancak teminat hesapları, müşteri hesapları, geçici hesaplar vb. diğer hesaplarda muhasebeleştirilen zarar | D264: A6C18 | E264: =IFERROR(INDEX('QAR Kodları'!$B:$B,MATCH(D264,'QAR Kodları'!$A:$A,0)),"KOD BULUNAMADI") -> Other capital receipts (not included else where) | F264: Genel / En yakın | G264: Türev işlem kâr/zarar ödemesi; QAR'da türev kodu yok. Forward iptali ise A2F01 de düşünülebilir. | H264: 8) Teminat İşlemleri (Finansal Ürün İlişkili)
A265: =B265&"-"&D265 -> 7631-A6C18 | B265: 7631 | C265: Bankanın kendi adına yurtdışı yerleşik kişiler ile gerçekleştirdiği opsiyon tipi işlem sonucu elde ettiği zarar | D265: A6C18 | E265: =IFERROR(INDEX('QAR Kodları'!$B:$B,MATCH(D265,'QAR Kodları'!$A:$A,0)),"KOD BULUNAMADI") -> Other capital receipts (not included else where) | F265: Genel / En yakın | G265: Türev işlem kâr/zarar ödemesi; QAR'da türev kodu yok. Forward iptali ise A2F01 de düşünülebilir. | H265: 8) Teminat İşlemleri (Finansal Ürün İlişkili)
A266: =B266&"-"&D266 -> T7631-A6C18 | B266: T7631 | C266: Bankanın kendi adına yurtdışı yerleşik kişiler ile gerçekleştirdiği opsiyon tipi işlemler için, muhabir hesaplarına yansımayan ancak teminat hesapları, müşteri hesapları, geçici hesaplar vb. diğer hesaplarda muhasebeleştirilen zarar | D266: A6C18 | E266: =IFERROR(INDEX('QAR Kodları'!$B:$B,MATCH(D266,'QAR Kodları'!$A:$A,0)),"KOD BULUNAMADI") -> Other capital receipts (not included else where) | F266: Genel / En yakın | G266: Türev işlem kâr/zarar ödemesi; QAR'da türev kodu yok. Forward iptali ise A2F01 de düşünülebilir. | H266: 8) Teminat İşlemleri (Finansal Ürün İlişkili)
A267: =B267&"-"&D267 -> 7632-A6C18 | B267: 7632 | C267: Bankanın yurtiçinde yerleşik müşterisi adına yurtdışı yerleşik kişiler ile gerçekleştirdiği forward, futures ve swap işlemlerinden elde edilen zarar | D267: A6C18 | E267: =IFERROR(INDEX('QAR Kodları'!$B:$B,MATCH(D267,'QAR Kodları'!$A:$A,0)),"KOD BULUNAMADI") -> Other capital receipts (not included else where) | F267: Genel / En yakın | G267: Türev işlem kâr/zarar ödemesi; QAR'da türev kodu yok. Forward iptali ise A2F01 de düşünülebilir. | H267: 3) Döviz Swap İşlemleri; 8) Teminat İşlemleri (Finansal Ürün İlişkili)
A268: =B268&"-"&D268 -> 7633-A6C18 | B268: 7633 | C268: Bankanın yurtiçinde yerleşik müşterisi adına yurtdışı yerleşik kişiler ile gerçekleştirdiği opsiyon-tipi işlemlerden elde edilen zarar | D268: A6C18 | E268: =IFERROR(INDEX('QAR Kodları'!$B:$B,MATCH(D268,'QAR Kodları'!$A:$A,0)),"KOD BULUNAMADI") -> Other capital receipts (not included else where) | F268: Genel / En yakın | G268: Türev işlem kâr/zarar ödemesi; QAR'da türev kodu yok. Forward iptali ise A2F01 de düşünülebilir. | H268: 8) Teminat İşlemleri (Finansal Ürün İlişkili)
A269: =B269&"-"&D269 -> 7634-A6C18 | B269: 7634 | C269: Bankanın yurtdışında yerleşik müşterisi adına yurtiçi yerleşik kişiler ile gerçekleştirdiği forward, futures ve swap işlemlerinden elde edilen kar transferi | D269: A6C18 | E269: =IFERROR(INDEX('QAR Kodları'!$B:$B,MATCH(D269,'QAR Kodları'!$A:$A,0)),"KOD BULUNAMADI") -> Other capital receipts (not included else where) | F269: Genel / En yakın | G269: Türev işlem kâr/zarar ödemesi; QAR'da türev kodu yok. Forward iptali ise A2F01 de düşünülebilir. | H269: 8) Teminat İşlemleri (Finansal Ürün İlişkili)
A270: =B270&"-"&D270 -> 7635-A6C18 | B270: 7635 | C270: Bankanın yurtdışında yerleşik müşterisi adına yurtiçi yerleşik kişiler ile gerçekleştirdiği opsiyon-tipi işlemlerden elde edilen kar transferi | D270: A6C18 | E270: =IFERROR(INDEX('QAR Kodları'!$B:$B,MATCH(D270,'QAR Kodları'!$A:$A,0)),"KOD BULUNAMADI") -> Other capital receipts (not included else where) | F270: Genel / En yakın | G270: Türev işlem kâr/zarar ödemesi; QAR'da türev kodu yok. Forward iptali ise A2F01 de düşünülebilir. | H270: 8) Teminat İşlemleri (Finansal Ürün İlişkili)
A271: =B271&"-"&D271 -> 7636-A6C18 | B271: 7636 | C271: Bankanın kendi adına yurtiçi yerleşik kişiler ile gerçekleştirdiği her türlü türev işlemlerinden elde ettiği zarar ve ödenen opsiyon primi | D271: A6C18 | E271: =IFERROR(INDEX('QAR Kodları'!$B:$B,MATCH(D271,'QAR Kodları'!$A:$A,0)),"KOD BULUNAMADI") -> Other capital receipts (not included else where) | F271: Genel / En yakın | G271: Türev işlem kâr/zarar ödemesi; QAR'da türev kodu yok. Forward iptali ise A2F01 de düşünülebilir. | H271: 8) Teminat İşlemleri (Finansal Ürün İlişkili)
A272: =B272&"-"&D272 -> 7640-A6C18 | B272: 7640 | C272: Bankanın kendi adına satın aldığı opsiyon sözleşmesi için yurtdışına transfer edilen prim | D272: A6C18 | E272: =IFERROR(INDEX('QAR Kodları'!$B:$B,MATCH(D272,'QAR Kodları'!$A:$A,0)),"KOD BULUNAMADI") -> Other capital receipts (not included else where) | F272: Genel / En yakın | G272: Opsiyon primi; QAR'da türev/opsiyon kodu yok. | H272: 5) Döviz Opsiyon İşlemleri
A273: =B273&"-"&D273 -> 7641-A6C18 | B273: 7641 | C273: Bankanın yurtiçinde yerleşik müşterisi hesabına satın aldığı opsiyon sözleşmesi için yurtdışına transfer edilen prim | D273: A6C18 | E273: =IFERROR(INDEX('QAR Kodları'!$B:$B,MATCH(D273,'QAR Kodları'!$A:$A,0)),"KOD BULUNAMADI") -> Other capital receipts (not included else where) | F273: Genel / En yakın | G273: Opsiyon primi; QAR'da türev/opsiyon kodu yok. | H273: 5) Döviz Opsiyon İşlemleri
A274: =B274&"-"&D274 -> 7642-A6C18 | B274: 7642 | C274: Bankanın yurtdışında yerleşik müşterisi adına yurtiçine sattığı opsiyon sözleşmesi priminin yurtdışına transferi | D274: A6C18 | E274: =IFERROR(INDEX('QAR Kodları'!$B:$B,MATCH(D274,'QAR Kodları'!$A:$A,0)),"KOD BULUNAMADI") -> Other capital receipts (not included else where) | F274: Genel / En yakın | G274: Opsiyon primi; QAR'da türev/opsiyon kodu yok. | H274: 5) Döviz Opsiyon İşlemleri
...

Sheet QAR Kodları
A1: QAR PoP Kodu | B1: Purpose of Payment Narration (EN) | C1: Eşleşen İst. Kodu Sayısı
A2: A1A01 | B2: Value of export bills negotiated/purchased/discounted etc | C2: =COUNTIF(Eşleştirme!$D$2:$D$282,A2) -> 3
A3: A1A02 | B3: Realization of export bills (in respect of goods) sent on collection (full invoice value) | C3: =COUNTIF(Eşleştirme!$D$2:$D$282,A3) -> 1
A4: A1A03 | B4: Advance receipts against export contracts (export of goods only) | C4: =COUNTIF(Eşleştirme!$D$2:$D$282,A4) -> 1
A5: A2A04 | B5: Freight on exports-shipping companies | C5: =COUNTIF(Eşleştirme!$D$2:$D$282,A5) -> 3
A6: A2A10 | B6: Freight on exports-airlines companies | C6: =COUNTIF(Eşleştirme!$D$2:$D$282,A6) -> 3
A7: A2A01 | B7: Inward remittance on account of surplus freight/passenger fare by Qatari shipping companies operating abroad | C7: =COUNTIF(Eşleştirme!$D$2:$D$282,A7) -> 1
A8: A2A02 | B8: Operating expenses of foreign shipping companies operating in Qatar | C8: =COUNTIF(Eşleştirme!$D$2:$D$282,A8) -> 0
A9: A2A05 | B9: Receipt towards operational leasing (with crew) shipping companies | C9: =COUNTIF(Eşleştirme!$D$2:$D$282,A9) -> 0
A10: A2A07 | B10: Inward remittance of surplus freight/passenger fare by Qatari airlines companies operating abroad | C10: =COUNTIF(Eşleştirme!$D$2:$D$282,A10) -> 1
A11: A2A08 | B11: Receipts on account of operating expenses of foreign airlines companies operating in Qatar | C11: =COUNTIF(Eşleştirme!$D$2:$D$282,A11) -> 0
A12: A2A11 | B12: Receipts towards operational leasing (with crew) airlines companies | C12: =COUNTIF(Eşleştirme!$D$2:$D$282,A12) -> 0
A13: A2A13 | B13: Receipts towards other transportation services (stevedoring demurrage port handling charges etc | C13: =COUNTIF(Eşleştirme!$D$2:$D$282,A13) -> 14
... A86: A7C03 | B86: Receipts by residents from residents | C86: =COUNTIF(Eşleştirme!$D$2:$D$282,A86) -> 0
A88: Kaynak: Qatar Central Bank 2024 (kullanıcının paylaştığı QAR-Purpose-Codes.pdf). PDF'te kesik görünen açıklamalar olduğu gibi aktarılmıştır.
